models/__init__.py
models/common.py
models/experimental.py
models/export.py
models/yolo.py
utils/__init__.py
utils/activations.py
utils/datasets.py
utils/general.py
utils/google_utils.py
utils/torch_utils.py
yolov5/__init__.py
yolov5/calc_rect.py
yolov5/detect.py
yolov5/eval.py
yolov5/models/__init__.py
yolov5/models/common.py
yolov5/models/experimental.py
yolov5/models/export.py
yolov5/models/yolo.py
yolov5/utils/__init__.py
yolov5/utils/activations.py
yolov5/utils/datasets.py
yolov5/utils/general.py
yolov5/utils/google_utils.py
yolov5/utils/torch_utils.py
yolov5_evaluator-0.0.21.dist-info/METADATA
yolov5_evaluator-0.0.21.dist-info/WHEEL
yolov5_evaluator-0.0.21.dist-info/top_level.txt
yolov5_evaluator-0.0.21.dist-info/RECORD
